{
  "indexes": [
    {
      "collectionGroup": "documents",
      "queryScope": "COLLECTION",
      "fields": [
        {
          "fieldPath": "userId",
          "order": "ASCENDING"
        },
        {
          "fieldPath": "createdAt",
          "order": "DESCENDING"
        }
      ]
    },
    {
      "collectionGroup": "documents",
      "queryScope": "COLLECTION",
      "fields": [
        {
          "fieldPath": "userId",
          "order": "ASCENDING"
        },
        {
          "fieldPath": "status",
          "order": "ASCENDING"
        },
        {
          "fieldPath": "updatedAt",
          "order": "DESCENDING"
        }
      ]
    },
    {
      "collectionGroup": "documents",
      "queryScope": "COLLECTION",
      "fields": [
        {
          "fieldPath": "userId",
          "order": "ASCENDING"
        },
        {
          "fieldPath": "type",
          "order": "ASCENDING"
        },
        {
          "fieldPath": "createdAt",
          "order": "DESCENDING"
        }
      ]
    },
    {
      "collectionGroup": "documents",
      "queryScope": "COLLECTION",
      "fields": [
        {
          "fieldPath": "tags",
          "arrayConfig": "CONTAINS"
        },
        {
          "fieldPath": "userId",
          "order": "ASCENDING"
        },
        {
          "fieldPath": "createdAt",
          "order": "DESCENDING"
        }
      ]
    },
    {
      "collectionGroup": "analysis",
      "queryScope": "COLLECTION",
      "fields": [
        {
          "fieldPath": "documentId",
          "order": "ASCENDING"
        },
        {
          "fieldPath": "type",
          "order": "ASCENDING"
        },
        {
          "fieldPath": "createdAt",
          "order": "DESCENDING"
        }
      ]
    },
    {
      "collectionGroup": "comments",
      "queryScope": "COLLECTION",
      "fields": [
        {
          "fieldPath": "documentId",
          "order": "ASCENDING"
        },
        {
          "fieldPath": "createdAt",
          "order": "ASCENDING"
        }
      ]
    },
    {
      "collectionGroup": "notifications",
      "queryScope": "COLLECTION",
      "fields": [
        {
          "fieldPath": "userId",
          "order": "ASCENDING"
        },
        {
          "fieldPath": "read",
          "order": "ASCENDING"
        },
        {
          "fieldPath": "createdAt",
          "order": "DESCENDING"
        }
      ]
    },
    {
      "collectionGroup": "notifications",
      "queryScope": "COLLECTION",
      "fields": [
        {
          "fieldPath": "userId",
          "order": "ASCENDING"
        },
        {
          "fieldPath": "type",
          "order": "ASCENDING"
        },
        {
          "fieldPath": "createdAt",
          "order": "DESCENDING"
        }
      ]
    },
    {
      "collectionGroup": "shared-documents",
      "queryScope": "COLLECTION",
      "fields": [
        {
          "fieldPath": "sharedWith",
          "arrayConfig": "CONTAINS"
        },
        {
          "fieldPath": "createdAt",
          "order": "DESCENDING"
        }
      ]
    },
    {
      "collectionGroup": "teams",
      "queryScope": "COLLECTION",
      "fields": [
        {
          "fieldPath": "members",
          "arrayConfig": "CONTAINS"
        },
        {
          "fieldPath": "updatedAt",
          "order": "DESCENDING"
        }
      ]
    },
    {
      "collectionGroup": "subscriptions",
      "queryScope": "COLLECTION",
      "fields": [
        {
          "fieldPath": "userId",
          "order": "ASCENDING"
        },
        {
          "fieldPath": "status",
          "order": "ASCENDING"
        },
        {
          "fieldPath": "updatedAt",
          "order": "DESCENDING"
        }
      ]
    },
    {
      "collectionGroup": "payments",
      "queryScope": "COLLECTION",
      "fields": [
        {
          "fieldPath": "userId",
          "order": "ASCENDING"
        },
        {
          "fieldPath": "status",
          "order": "ASCENDING"
        },
        {
          "fieldPath": "createdAt",
          "order": "DESCENDING"
        }
      ]
    },
    {
      "collectionGroup": "system-logs",
      "queryScope": "COLLECTION",
      "fields": [
        {
          "fieldPath": "level",
          "order": "ASCENDING"
        },
        {
          "fieldPath": "timestamp",
          "order": "DESCENDING"
        }
      ]
    },
    {
      "collectionGroup": "system-logs",
      "queryScope": "COLLECTION",
      "fields": [
        {
          "fieldPath": "service",
          "order": "ASCENDING"
        },
        {
          "fieldPath": "timestamp",
          "order": "DESCENDING"
        }
      ]
    },
    {
      "collectionGroup": "analytics",
      "queryScope": "COLLECTION",
      "fields": [
        {
          "fieldPath": "event",
          "order": "ASCENDING"
        },
        {
          "fieldPath": "timestamp",
          "order": "DESCENDING"
        }
      ]
    },
    {
      "collectionGroup": "analytics",
      "queryScope": "COLLECTION",
      "fields": [
        {
          "fieldPath": "userId",
          "order": "ASCENDING"
        },
        {
          "fieldPath": "timestamp",
          "order": "DESCENDING"
        }
      ]
    }
  ],
  "fieldOverrides": [
    {
      "collectionGroup": "documents",
      "fieldPath": "content",
      "indexes": [
        {
          "order": "ASCENDING",
          "queryScope": "COLLECTION"
        },
        {
          "arrayConfig": "CONTAINS",
          "queryScope": "COLLECTION"
        }
      ]
    }
  ]
}